{"cameraMode":{"drawMode":0,"name":"Shaded","section":"Shading Mode"},"sceneLighting":false,"audioPlay":false,"sceneViewState":{"m_AlwaysRefresh":false,"showFog":true,"showSkybox":false,"showFlares":true,"showImageEffects":true,"showParticleSystems":true,"showVisualEffectGraphs":true,"m_FxEnabled":true},"in2DMode":false,"pivot":{"x":-2.874030590057373,"y":1.8524975776672364,"z":-2.9115099906921388},"rotation":{"x":0.06444358825683594,"y":-0.022325759753584863,"z":0.0013941657962277532,"w":0.9977174401283264},"size":0.4897332489490509,"orthographic":false}